{
  "voicevox_url": "http://localhost:50021",
  "speakers": {
    "ずんだもん": 3,
    "めたん": 2
  },
  "speed_scale": 1.14,
  "inter_line_silence": 0.3,
  "scene_end_padding": 0.5,
  "scenes": [
    {
      "id": 0,
      "title": "なぜ画像形式は多いのか",
      "lines": [
        {
          "speaker": "めたん",
          "text": "ねえずんだもん、ずっと気になってたことがあるんですけど。"
        },
        {
          "speaker": "ずんだもん",
          "text": "なんだ？"
        },
        {
          "speaker": "めたん",
          "text": "JPEG、PNG、GIF、WebP、AVIF……画像形式って多すぎませんの？"
        },
        {
          "speaker": "ずんだもん",
          "text": "ああ、たしかによく聞かれる疑問なのだ。"
        },
        {
          "speaker": "めたん",
          "text": "全部「画像」なのに、なんでこんなにたくさんあるんですの？"
        }
      ]
    },
    {
      "id": 1,
      "title": "1種類しかない世界",
      "lines": [
        {
          "speaker": "ずんだもん",
          "text": "いい質問なのだ。じゃあ、こんな思考実験をしてみてほしいのだ。"
        },
        {
          "speaker": "ずんだもん",
          "text": "もし世界に画像形式が1つしかなかったら、何が起きると思う？"
        },
        {
          "speaker": "めたん",
          "text": "えっと……1つで全部まかなえるなら、便利じゃないですの？"
        },
        {
          "speaker": "めたん",
          "text": "ファイルのやり取りも簡単だし、変換の必要もないですわよね。"
        },
        {
          "speaker": "ずんだもん",
          "text": "一見そう思うよね。でも実はこれ、とんでもないことになるのだ。"
        }
      ]
    },
    {
      "id": 2,
      "title": "万能形式の矛盾",
      "lines": [
        {
          "speaker": "ずんだもん",
          "text": "たとえばその形式が「写真が得意な形式」だったとしよう。"
        },
        {
          "speaker": "ずんだもん",
          "text": "写真を保存するときはきれいで小さくなる。完璧なのだ。"
        },
        {
          "speaker": "ずんだもん",
          "text": "でもロゴを保存したら？ 輪郭がボヤけてガビガビになる。"
        },
        {
          "speaker": "めたん",
          "text": "うーん、それは困りますわね。"
        },
        {
          "speaker": "ずんだもん",
          "text": "動くスタンプを作りたい？ アニメーションには対応していない。"
        },
        {
          "speaker": "ずんだもん",
          "text": "背景を透明にしたい？ それもできない。"
        },
        {
          "speaker": "めたん",
          "text": "全部ダメじゃないですの！"
        },
        {
          "speaker": "ずんだもん",
          "text": "逆に「ロゴが得意な形式」1つだけにしたらどうなるか。"
        },
        {
          "speaker": "ずんだもん",
          "text": "今度はスマホで撮った写真がファイルサイズ巨大になって送れないのだ。"
        },
        {
          "speaker": "めたん",
          "text": "つまり、どの形式を選んでも何かが犠牲になるってことですの？"
        },
        {
          "speaker": "ずんだもん",
          "text": "その通り。「万能な画像形式」というのは、原理的にありえないのだ。"
        },
        {
          "speaker": "ずんだもん",
          "text": "この動画では、その理由を一緒に解き明かしていくのだ。"
        },
        {
          "speaker": "めたん",
          "text": "ぜひ教えてくださいませ！"
        }
      ]
    },
    {
      "id": 3,
      "title": "圧縮 = 引っ越しの荷造り",
      "lines": [
        {
          "speaker": "ずんだもん",
          "text": "画像形式の違いを知るには、まず「圧縮」の正体を理解する必要があるのだ。"
        },
        {
          "speaker": "ずんだもん",
          "text": "引っ越しの荷造りをイメージしてほしいのだ。"
        },
        {
          "speaker": "めたん",
          "text": "荷造り？ 画像と何の関係がありますの？"
        },
        {
          "speaker": "ずんだもん",
          "text": "ちょっと考えてみてほしいのだ。"
        },
        {
          "speaker": "ずんだもん",
          "text": "荷物を全部そのまま箱に放り込んだら、ダンボールが何十箱にもなるよね。"
        },
        {
          "speaker": "ずんだもん",
          "text": "これが「無圧縮」の画像、つまりBMPなのだ。"
        },
        {
          "speaker": "めたん",
          "text": "BMP？ たまに見かけるけど、使ってる人は少ないですわよね。"
        },
        {
          "speaker": "ずんだもん",
          "text": "そう、まさにそのサイズの巨大さが理由なのだ。"
        },
        {
          "speaker": "ずんだもん",
          "text": "1920×1080の画像1枚で、約6メガバイトにもなるのだ。"
        },
        {
          "speaker": "めたん",
          "text": "6メガバイト！？ たった1枚で、ですの？"
        },
        {
          "speaker": "ずんだもん",
          "text": "そう。スマホの写真100枚撮ったら600メガバイト。すぐにスマホがパンクするのだ。"
        },
        {
          "speaker": "めたん",
          "text": "それは確かに困りますわね……。"
        }
      ]
    },
    {
      "id": 4,
      "title": "可逆圧縮",
      "lines": [
        {
          "speaker": "ずんだもん",
          "text": "じゃあどうする？ まず「服を丁寧に畳んで隙間なく詰める」方法があるのだ。"
        },
        {
          "speaker": "ずんだもん",
          "text": "同じ色が続いているところを「この色が100個並んでるよ」とまとめるのだ。"
        },
        {
          "speaker": "ずんだもん",
          "text": "これが「可逆圧縮」。PNGやGIFがやっていることなのだ。"
        },
        {
          "speaker": "めたん",
          "text": "畳んだだけなら、また広げれば元通りですわよね？"
        },
        {
          "speaker": "ずんだもん",
          "text": "その通り。1ビットも情報を失わない。完全に元に戻せるのだ。"
        },
        {
          "speaker": "めたん",
          "text": "じゃあ全部これでいいじゃないですの？"
        }
      ]
    },
    {
      "id": 5,
      "title": "非可逆圧縮",
      "lines": [
        {
          "speaker": "ずんだもん",
          "text": "ところがね、畳むだけだと限界があるのだ。"
        },
        {
          "speaker": "ずんだもん",
          "text": "なぜかというと、写真みたいに色がグラデーションで変わっていく画像は……"
        },
        {
          "speaker": "ずんだもん",
          "text": "「同じ色の繰り返し」がほとんどないのだ。隣のピクセルと色が全部違う。"
        },
        {
          "speaker": "ずんだもん",
          "text": "畳んでも全然小さくならないのだ。"
        },
        {
          "speaker": "めたん",
          "text": "なるほど……写真は色がどんどん変わるから、まとめようがないんですわね。"
        },
        {
          "speaker": "ずんだもん",
          "text": "そこで「もう着ない服は思い切って捨てる」方法があるのだ。"
        },
        {
          "speaker": "めたん",
          "text": "捨てちゃうんですの！？"
        },
        {
          "speaker": "ずんだもん",
          "text": "そう。これが「非可逆圧縮」。JPEGがやっていることなのだ。"
        },
        {
          "speaker": "ずんだもん",
          "text": "捨てた分だけ劇的に小さくなる。でも、捨てた情報は二度と戻らない。"
        }
      ]
    },
    {
      "id": 6,
      "title": "トレードオフの本質",
      "lines": [
        {
          "speaker": "めたん",
          "text": "つまり、サイズを取るか画質を取るかってことですの？"
        },
        {
          "speaker": "ずんだもん",
          "text": "大正解なのだ！ これが画像圧縮の最も根本的なトレードオフなのだ。"
        },
        {
          "speaker": "ずんだもん",
          "text": "完全に元に戻せるけどあまり小さくならないか……"
        },
        {
          "speaker": "ずんだもん",
          "text": "劇的に小さくなるけど情報が失われるか。"
        },
        {
          "speaker": "ずんだもん",
          "text": "この2つは物理法則のように両立できないのだ。"
        },
        {
          "speaker": "めたん",
          "text": "うーん、どっちかしか選べないんですわね。"
        },
        {
          "speaker": "ずんだもん",
          "text": "そしてここが超重要なポイントなのだ。"
        },
        {
          "speaker": "ずんだもん",
          "text": "この「トレードオフ」こそが、画像形式が増え続ける根本原因の1つなのだ。"
        }
      ]
    },
    {
      "id": 7,
      "title": "JPEGの圧縮パイプライン",
      "lines": [
        {
          "speaker": "ずんだもん",
          "text": "じゃあJPEGは具体的に「何を捨てている」のか、見てみるのだ。"
        },
        {
          "speaker": "ずんだもん",
          "text": "JPEGはまず画像を8×8ピクセルの小さなブロックに分割するのだ。"
        },
        {
          "speaker": "ずんだもん",
          "text": "そして各ブロックの模様を「波の組み合わせ」に変換するのだ。"
        },
        {
          "speaker": "めたん",
          "text": "波？ 画像なのに波ですの？"
        },
        {
          "speaker": "ずんだもん",
          "text": "不思議だよね。でもこれが天才的な発想なのだ。"
        },
        {
          "speaker": "ずんだもん",
          "text": "大きくゆっくりした波が「ぼんやりした明暗」を表して……"
        },
        {
          "speaker": "ずんだもん",
          "text": "細かくて速い波が「くっきりした輪郭や模様」を表すのだ。"
        }
      ]
    },
    {
      "id": 8,
      "title": "高周波を捨てる戦略",
      "lines": [
        {
          "speaker": "ずんだもん",
          "text": "そしてここがJPEGの天才的なところなのだ。"
        },
        {
          "speaker": "ずんだもん",
          "text": "人間の目は、ゆっくりした波には敏感だけど……"
        },
        {
          "speaker": "ずんだもん",
          "text": "細かい波の違いはほとんど区別できないのだ。"
        },
        {
          "speaker": "めたん",
          "text": "えっ、そうなんですの？"
        },
        {
          "speaker": "ずんだもん",
          "text": "たとえば遠くの山の写真を見てみてほしいのだ。"
        },
        {
          "speaker": "ずんだもん",
          "text": "山の稜線はくっきりわかるけど、木の葉っぱ1枚1枚は見えないよね。"
        },
        {
          "speaker": "めたん",
          "text": "確かに、言われてみればそうですわね。"
        },
        {
          "speaker": "ずんだもん",
          "text": "その「見えない部分」を捨てても、人間の目にはほとんど同じに見えるのだ。"
        },
        {
          "speaker": "ずんだもん",
          "text": "もっと言うと、人間の目は色の変化には明るさの変化ほど敏感じゃないのだ。"
        },
        {
          "speaker": "ずんだもん",
          "text": "だからJPEGは色の情報をさらに大胆に間引くのだ。"
        },
        {
          "speaker": "めたん",
          "text": "つまり、人間の目を騙してるってことですの？"
        },
        {
          "speaker": "ずんだもん",
          "text": "まさに！ 「人間の知覚のバグ」を利用しているのだ。"
        },
        {
          "speaker": "ずんだもん",
          "text": "だからJPEGは写真を10分の1以下に小さくできる。"
        },
        {
          "speaker": "ずんだもん",
          "text": "でも……この方法には致命的な弱点があるのだ。"
        }
      ]
    },
    {
      "id": 9,
      "title": "JPEGが苦手なもの",
      "lines": [
        {
          "speaker": "めたん",
          "text": "致命的な弱点って何ですの？"
        },
        {
          "speaker": "ずんだもん",
          "text": "こういう経験ないか？ ロゴやテキストをJPEGで保存したら……"
        },
        {
          "speaker": "ずんだもん",
          "text": "輪郭の周りにモヤモヤしたノイズが出たこと。"
        },
        {
          "speaker": "めたん",
          "text": "あー！ あれ「モスキートノイズ」って言うんですわよね？"
        },
        {
          "speaker": "ずんだもん",
          "text": "その通り。蚊が飛んでるみたいだからそう呼ばれるのだ。"
        },
        {
          "speaker": "ずんだもん",
          "text": "さらに、画像全体がブロック状にガビガビになる。"
        },
        {
          "speaker": "ずんだもん",
          "text": "これが「ブロックノイズ」なのだ。"
        }
      ]
    },
    {
      "id": 10,
      "title": "写真向き vs ロゴ向き",
      "lines": [
        {
          "speaker": "ずんだもん",
          "text": "なぜこうなるか、さっきの話を思い出してほしいのだ。"
        },
        {
          "speaker": "ずんだもん",
          "text": "JPEGは「細かい波」を捨てるんだったよね？"
        },
        {
          "speaker": "めたん",
          "text": "はい。人間の目に見えにくい部分を捨てるって……あ！"
        },
        {
          "speaker": "めたん",
          "text": "ロゴのくっきりしたエッジって、まさに「細かい波」ですの！？"
        },
        {
          "speaker": "ずんだもん",
          "text": "大正解なのだ！ JPEGが捨てる情報こそが……"
        },
        {
          "speaker": "ずんだもん",
          "text": "ロゴやテキストの「くっきり感」を作る情報だったのだ。"
        },
        {
          "speaker": "めたん",
          "text": "写真だと見えない情報が、ロゴだとめちゃくちゃ大事ってことですわね。"
        },
        {
          "speaker": "ずんだもん",
          "text": "その通り。同じ「捨てる」でも、画像の種類で被害が全然違うのだ。"
        }
      ]
    },
    {
      "id": 11,
      "title": "再保存の劣化蓄積",
      "lines": [
        {
          "speaker": "ずんだもん",
          "text": "しかもJPEGには、もう一つ怖い性質があるのだ。"
        },
        {
          "speaker": "ずんだもん",
          "text": "保存するたびに情報が捨てられるから……"
        },
        {
          "speaker": "ずんだもん",
          "text": "保存→編集→保存を繰り返すと、どんどん劣化するのだ。"
        },
        {
          "speaker": "めたん",
          "text": "え、保存するだけで壊れていくんですの！？"
        },
        {
          "speaker": "ずんだもん",
          "text": "そう。いわば「コピーのコピーのコピー」で劣化していくのだ。"
        },
        {
          "speaker": "ずんだもん",
          "text": "実際にJPEGを50回再保存した実験では、元の画像が判別できないほど壊れたのだ。"
        },
        {
          "speaker": "めたん",
          "text": "50回で判別不能……それは恐ろしいですわね。"
        },
        {
          "speaker": "ずんだもん",
          "text": "これは非可逆圧縮の宿命なのだ。"
        }
      ]
    },
    {
      "id": 12,
      "title": "だからPNGが必要だった",
      "lines": [
        {
          "speaker": "ずんだもん",
          "text": "だから、「1ビットも情報を失わない」画像形式が必要だったのだ。"
        },
        {
          "speaker": "ずんだもん",
          "text": "それがPNG。ロゴ、アイコン、スクリーンショットに最適なのだ。"
        },
        {
          "speaker": "ずんだもん",
          "text": "しかもPNGは半透明が使えるのだ。"
        },
        {
          "speaker": "ずんだもん",
          "text": "たとえばWebサイトのロゴを、どんな背景色の上にも重ねられるのだ。"
        },
        {
          "speaker": "めたん",
          "text": "なるほど！ JPEGとPNGが両方存在する理由がわかりましたわ！"
        },
        {
          "speaker": "めたん",
          "text": "JPEGは写真用、PNGはロゴやイラスト用なんですわね。"
        },
        {
          "speaker": "めたん",
          "text": "でもそれなら、GIFって何のために必要なんですの？"
        }
      ]
    },
    {
      "id": 13,
      "title": "GIF誕生：1987年",
      "lines": [
        {
          "speaker": "ずんだもん",
          "text": "GIFの話は、実はただの技術の話じゃないのだ。"
        },
        {
          "speaker": "ずんだもん",
          "text": "特許と政治が画像形式の歴史を変えた、ドラマチックな物語なのだ。"
        },
        {
          "speaker": "ずんだもん",
          "text": "1987年、インターネットはまだ電話回線でつなぐ時代だったのだ。"
        },
        {
          "speaker": "めたん",
          "text": "モデムがピーガガガーって鳴るやつですわね。"
        }
      ]
    },
    {
      "id": 14,
      "title": "モデム時代の制約",
      "lines": [
        {
          "speaker": "ずんだもん",
          "text": "当時のモデムは秒速300ビット。今のスマホの通信速度の数十万分の1なのだ。"
        },
        {
          "speaker": "ずんだもん",
          "text": "こんな環境で画像を送るには、とにかくファイルを軽くするしかない。"
        },
        {
          "speaker": "ずんだもん",
          "text": "そこでCompuServe社が考えたのが「色を256色に絞る」という大胆な割り切り。"
        },
        {
          "speaker": "めたん",
          "text": "1677万色から256色って、すごい思い切りですわね。"
        },
        {
          "speaker": "ずんだもん",
          "text": "でも256色あれば、イラストやアイコンには十分なのだ。"
        },
        {
          "speaker": "ずんだもん",
          "text": "でもこの割り切りのおかげで、ファイルサイズが劇的に小さくなったのだ。"
        },
        {
          "speaker": "ずんだもん",
          "text": "しかも1989年には、パラパラ漫画のようにアニメーションもできるようにした。"
        },
        {
          "speaker": "めたん",
          "text": "1987年にもうアニメーションを考えていたんですの？ 先見の明がありますわね。"
        }
      ]
    },
    {
      "id": 15,
      "title": "LZW特許問題",
      "lines": [
        {
          "speaker": "ずんだもん",
          "text": "ところがここで事件が起きるのだ。"
        },
        {
          "speaker": "ずんだもん",
          "text": "GIFが内部で使っていた「LZW」という圧縮技術に、特許があったのだ。"
        },
        {
          "speaker": "ずんだもん",
          "text": "Unisysという会社が、1994年に突然こう宣言した。"
        },
        {
          "speaker": "ずんだもん",
          "text": "「GIFを使うソフトは、全部ライセンス料を払え」と。"
        },
        {
          "speaker": "めたん",
          "text": "え！？ みんな無料で使ってたのに、いきなりですの！？"
        },
        {
          "speaker": "ずんだもん",
          "text": "そう。何年も自由に使わせておいて、普及してから「金を払え」なのだ。"
        }
      ]
    },
    {
      "id": 16,
      "title": "Burn All GIFs運動",
      "lines": [
        {
          "speaker": "ずんだもん",
          "text": "これにインターネットのコミュニティが大激怒したのだ。"
        },
        {
          "speaker": "ずんだもん",
          "text": "「Burn All GIFs」──つまり「GIFを全部燃やせ」という運動まで起きた。"
        },
        {
          "speaker": "めたん",
          "text": "すごい名前ですわね……。"
        },
        {
          "speaker": "ずんだもん",
          "text": "そしてこの怒りのエネルギーが、新しい画像形式を生み出したのだ。"
        }
      ]
    },
    {
      "id": 17,
      "title": "PNG誕生：1995年",
      "lines": [
        {
          "speaker": "めたん",
          "text": "それがPNGですの！？"
        },
        {
          "speaker": "ずんだもん",
          "text": "その通りなのだ！ PNGは「Portable Network Graphics」の略で……"
        },
        {
          "speaker": "ずんだもん",
          "text": "特許に縛られない、完全にフリーな画像形式として1995年に誕生したのだ。"
        },
        {
          "speaker": "ずんだもん",
          "text": "面白いことに、PNGという名前は「PNG is Not GIF」の略でもあるのだ。"
        },
        {
          "speaker": "めたん",
          "text": "GIFへの対抗意識がそのまま名前になってるんですわね。"
        },
        {
          "speaker": "ずんだもん",
          "text": "ちなみにGIFの特許は2003年に失効した。"
        },
        {
          "speaker": "ずんだもん",
          "text": "でもその頃にはもうPNGが広まっていて、GIFの代替として定着していたのだ。"
        },
        {
          "speaker": "めたん",
          "text": "特許が技術の歴史を変えたんですわね……。"
        }
      ]
    },
    {
      "id": 18,
      "title": "GIFアニメの復活",
      "lines": [
        {
          "speaker": "ずんだもん",
          "text": "でもGIFの物語はここで終わらないのだ。"
        },
        {
          "speaker": "ずんだもん",
          "text": "2010年、スティーブ・ジョブズがiPhoneでFlashを排除したのだ。"
        },
        {
          "speaker": "ずんだもん",
          "text": "当時Webの動くコンテンツはほとんどFlashで作られていたのだ。"
        },
        {
          "speaker": "ずんだもん",
          "text": "それが使えなくなって、代わりにGIFアニメがSNSで大復活を遂げたのだ。"
        },
        {
          "speaker": "めたん",
          "text": "すごい！ GIFって何度も復活してますのね。"
        },
        {
          "speaker": "ずんだもん",
          "text": "2012年にはオックスフォード辞典のアメリカ版で「GIF」が年間最優秀語に選ばれたのだ。"
        },
        {
          "speaker": "めたん",
          "text": "画像形式の名前が「年間の言葉」ですの！？ それはすごいですわ。"
        },
        {
          "speaker": "ずんだもん",
          "text": "そう。技術的には古いけど、シンプルだからこそ生き残り続けているのだ。"
        },
        {
          "speaker": "ずんだもん",
          "text": "ここに面白いパターンがあるのだ。画像形式は技術だけでなく……"
        },
        {
          "speaker": "ずんだもん",
          "text": "特許、企業の戦略、社会の変化によっても運命が変わるということなのだ。"
        }
      ]
    },
    {
      "id": 19,
      "title": "3形式の得意・不得意",
      "lines": [
        {
          "speaker": "ずんだもん",
          "text": "さて、ここまでの話を整理すると……"
        },
        {
          "speaker": "ずんだもん",
          "text": "写真にはJPEG、ロゴにはPNG、アニメにはGIF。"
        },
        {
          "speaker": "ずんだもん",
          "text": "それぞれ得意なことが違うから、複数の形式が必要なのだ。"
        },
        {
          "speaker": "めたん",
          "text": "でも、最近はWebPとかAVIFとか新しいのも出てきてますわよね。"
        },
        {
          "speaker": "めたん",
          "text": "もしかして、ついに「万能な形式」ができたんですの？"
        }
      ]
    },
    {
      "id": 20,
      "title": "動画コーデックから画像へ",
      "lines": [
        {
          "speaker": "ずんだもん",
          "text": "ここからが面白いところなのだ。"
        },
        {
          "speaker": "ずんだもん",
          "text": "WebPもAVIFも、実は「動画の技術」から生まれているのだ。"
        },
        {
          "speaker": "めたん",
          "text": "動画から画像ですの？ 逆じゃなくて？"
        },
        {
          "speaker": "ずんだもん",
          "text": "そう。ちょっと考えてみてほしいのだ。"
        },
        {
          "speaker": "ずんだもん",
          "text": "動画って結局「1秒間に30枚の画像の連続」なのだ。"
        },
        {
          "speaker": "めたん",
          "text": "30枚も！？ そりゃ効率よく圧縮しないと大変ですわね。"
        },
        {
          "speaker": "ずんだもん",
          "text": "その通り。だから動画の圧縮技術は超高性能に進化してきたのだ。"
        },
        {
          "speaker": "ずんだもん",
          "text": "その技術で「1枚だけ」圧縮したらどうなるか……"
        },
        {
          "speaker": "ずんだもん",
          "text": "従来の画像形式より遥かに小さくできることに気づいたのだ。"
        }
      ]
    },
    {
      "id": 21,
      "title": "WebPとAVIFの圧縮率",
      "lines": [
        {
          "speaker": "めたん",
          "text": "どれくらい小さくなりますの？"
        },
        {
          "speaker": "ずんだもん",
          "text": "WebPはJPEGより25〜34%小さくなるのだ。"
        },
        {
          "speaker": "ずんだもん",
          "text": "AVIFに至っては、JPEGの約半分のサイズで同じ画質を実現するのだ。"
        },
        {
          "speaker": "めたん",
          "text": "半分！？ それはすごいですわ！"
        },
        {
          "speaker": "ずんだもん",
          "text": "同じ画質でファイルサイズ半分。Webページの読み込みが劇的に速くなるのだ。"
        },
        {
          "speaker": "ずんだもん",
          "text": "しかもどちらも透過もアニメーションも対応しているのだ。"
        },
        {
          "speaker": "めたん",
          "text": "じゃあもう全部WebPかAVIFにすればいいじゃないですの！"
        }
      ]
    },
    {
      "id": 22,
      "title": "次世代形式の制約",
      "lines": [
        {
          "speaker": "ずんだもん",
          "text": "……と思うよね。でもやっぱりトレードオフがあるのだ。"
        },
        {
          "speaker": "ずんだもん",
          "text": "WebPは色の深さが8ビットまで。HDR映像に対応していない。"
        },
        {
          "speaker": "ずんだもん",
          "text": "AVIFはエンコードがとても遅い。1枚の画像の変換に何秒もかかるのだ。"
        },
        {
          "speaker": "ずんだもん",
          "text": "たとえばInstagramのように1日に1億枚以上の写真がアップされるサービスでは……"
        },
        {
          "speaker": "ずんだもん",
          "text": "この遅さはサーバーのコスト的に致命的なのだ。"
        },
        {
          "speaker": "めたん",
          "text": "万能に見えて、まだ弱点があるんですわね。"
        },
        {
          "speaker": "ずんだもん",
          "text": "さっきの引っ越しのたとえで言えば……"
        },
        {
          "speaker": "ずんだもん",
          "text": "「最新の圧縮袋で服を超小さくできるけど、真空ポンプが遅くて時間がかかる」のだ。"
        },
        {
          "speaker": "めたん",
          "text": "あー、なるほど。小さくなっても作業時間が長すぎると困りますわね。"
        }
      ]
    },
    {
      "id": 23,
      "title": "JPEG XL論争",
      "lines": [
        {
          "speaker": "ずんだもん",
          "text": "そしてもう1つ、知っておくべきドラマがあるのだ。"
        },
        {
          "speaker": "ずんだもん",
          "text": "JPEG XLという形式は「最後の画像形式」を目指して作られたのだ。"
        },
        {
          "speaker": "ずんだもん",
          "text": "可逆も非可逆も、HDRもアニメも、既存JPEGの無劣化再圧縮も──全部入り。"
        },
        {
          "speaker": "めたん",
          "text": "すごい！ 今度こそ万能じゃないですの？"
        },
        {
          "speaker": "ずんだもん",
          "text": "ところがGoogleが2023年にChromeでJPEG XLのサポートを削除したのだ。"
        },
        {
          "speaker": "ずんだもん",
          "text": "「十分な関心がない」というのが理由だったけど……"
        },
        {
          "speaker": "ずんだもん",
          "text": "多くの開発者が「自社のWebPやAVIFを優遇してるだけだ」と批判したのだ。"
        },
        {
          "speaker": "めたん",
          "text": "技術の良し悪しだけじゃなく、企業の力関係も影響するってことですの？"
        },
        {
          "speaker": "ずんだもん",
          "text": "その通り。GIFの特許問題と同じ構造なことに気づいたか？"
        },
        {
          "speaker": "めたん",
          "text": "あ！ 確かに。どちらも「技術以外の力」で運命が決まってますわね。"
        },
        {
          "speaker": "ずんだもん",
          "text": "まさに。同じ歴史が、形を変えて何度も繰り返されているのだ。"
        },
        {
          "speaker": "ずんだもん",
          "text": "ちなみにJPEG XLは2025年にChromiumに復帰する動きも出てきているのだ。"
        },
        {
          "speaker": "ずんだもん",
          "text": "画像形式の戦いは、まだまだ続いているのだ。"
        }
      ]
    },
    {
      "id": 24,
      "title": "形式が増え続ける4つの原因",
      "lines": [
        {
          "speaker": "ずんだもん",
          "text": "さて、最初の問いに戻ろう。"
        },
        {
          "speaker": "ずんだもん",
          "text": "「なぜ画像形式はこんなにたくさんあるのか」。"
        },
        {
          "speaker": "めたん",
          "text": "最初は「1つでいいのに」って思ってましたわ。"
        },
        {
          "speaker": "めたん",
          "text": "でも今は全然違う気持ちですわ。"
        },
        {
          "speaker": "ずんだもん",
          "text": "答えは、大きく4つの理由に集約されるのだ。"
        }
      ]
    },
    {
      "id": 25,
      "title": "トレードオフの不可避性",
      "lines": [
        {
          "speaker": "ずんだもん",
          "text": "第1に、トレードオフの不可避性なのだ。"
        },
        {
          "speaker": "ずんだもん",
          "text": "ファイルサイズと画質。速度と機能。透過の有無。"
        },
        {
          "speaker": "ずんだもん",
          "text": "これらは物理法則のように、すべてを同時に最適化することは不可能なのだ。"
        },
        {
          "speaker": "ずんだもん",
          "text": "だからJPEGとPNGが共存するし、GIFも生き残っているのだ。"
        }
      ]
    },
    {
      "id": 26,
      "title": "特許・用途・覇権",
      "lines": [
        {
          "speaker": "ずんだもん",
          "text": "第2に、特許とライセンスの問題。GIFの特許がPNGを生んだように。"
        },
        {
          "speaker": "ずんだもん",
          "text": "第3に、新しい用途が常に生まれること。"
        },
        {
          "speaker": "ずんだもん",
          "text": "HDR、透過アニメ、Web表示速度──新しいニーズには新しい形式が必要なのだ。"
        },
        {
          "speaker": "ずんだもん",
          "text": "そして第4に、企業間の技術覇権争いなのだ。"
        },
        {
          "speaker": "ずんだもん",
          "text": "GoogleのWebP、AOMのAVIF、JPEG委員会のJPEG XL。"
        },
        {
          "speaker": "ずんだもん",
          "text": "技術だけでなく、誰が標準を握るかの戦いでもあるのだ。"
        }
      ]
    },
    {
      "id": 27,
      "title": "理解の転換",
      "lines": [
        {
          "speaker": "めたん",
          "text": "最初は「面倒くさい」って思ってたのが……"
        },
        {
          "speaker": "めたん",
          "text": "今は「全部ちゃんと理由があって存在してる」ってわかりましたわ。"
        },
        {
          "speaker": "ずんだもん",
          "text": "そうなのだ。画像形式の多様性は、バグじゃなくてフィーチャーなのだ。"
        },
        {
          "speaker": "ずんだもん",
          "text": "「なんで統一しないの？」じゃなくて、「統一できないからこそ多様なのだ」。"
        },
        {
          "speaker": "めたん",
          "text": "トレードオフがある限り、1つには絶対なれないんですわね。"
        },
        {
          "speaker": "ずんだもん",
          "text": "次にファイルを保存するとき、ちょっと立ち止まって考えてみてほしいのだ。"
        },
        {
          "speaker": "ずんだもん",
          "text": "写真なのか、イラストなのか、透過が必要なのか、アニメーションなのか。"
        },
        {
          "speaker": "ずんだもん",
          "text": "その答えによって最適な形式が変わる。それが画像形式の世界なのだ。"
        }
      ]
    },
    {
      "id": 28,
      "title": "多様性はフィーチャー",
      "lines": [
        {
          "speaker": "ずんだもん",
          "text": "そしてこの動画を見たあなたは、もう迷わず選べるはずなのだ。"
        },
        {
          "speaker": "めたん",
          "text": "写真はJPEG、ロゴはPNG、短いアニメはGIF……ですわよね。"
        },
        {
          "speaker": "ずんだもん",
          "text": "そう。そして速度重視のWebならWebP、最高画質ならAVIFなのだ。"
        },
        {
          "speaker": "めたん",
          "text": "なるほど！ 今日からは自信を持って選べそうですわ！"
        },
        {
          "speaker": "めたん",
          "text": "ずんだもん、ありがとうございましたわ！"
        },
        {
          "speaker": "ずんだもん",
          "text": "こちらこそ、一緒に勉強してくれてありがとうなのだ。"
        }
      ]
    }
  ]
}