{
  "scene_00_00.wav": "今日のテーマは「最近のwebアプリ重すぎ！」ですわ。",
  "scene_00_01.wav": "わかる！ ブラウザ開くだけでピーシーのファンが回り始めるのだ。",
  "scene_00_02.wav": "クロームのタブを10個開いたらメモリが数ギガバイト消えた、なんて経験ありませんこと？",
  "scene_00_03.wav": "あるある。タブを閉じた瞬間にピーシーが生き返るよね。",
  "scene_00_04.wav": "その実感、ちゃんとデータで裏付けられていますの。",
  "scene_00_05.wav": "今日はウェブがなぜこんなに重くなったのか、一緒に探っていきましょう。",
  "scene_01_00.wav": "具体的にどのくらい重くなってるの？",
  "scene_01_01.wav": "エイチティーティーピー アーカイブというデータベースが、世界中のウェブページを定期的に計測していますわ。",
  "scene_01_02.wav": "そのデータによると、ページサイズの中央値は2010年に約468キロバイトでしたの。",
  "scene_01_03.wav": "468キロバイト。画像数枚分くらいだね。",
  "scene_01_04.wav": "それが2015年には約2,000キロバイト。初めて2メガバイトの壁を超えたと話題になりましたわ。",
  "scene_01_05.wav": "2020年に約2,100キロバイト、そして2024年にはデスクトップで約2,600キロバイトですの。",
  "scene_01_06.wav": "15年で5倍以上！？ 右肩上がりが止まらないんだね。",
  "scene_01_07.wav": "ただし計測方法や対象サイトによって数字は変わりますわ。それでも増加傾向は明らかですの。",
  "scene_01_08.wav": "なんでこんなに増え続けてるの？",
  "scene_02_00.wav": "昔のウェブページってどのくらい軽かったの？",
  "scene_02_01.wav": "象徴的な例がありますわ。1996年に公開された映画スペース ジャムの公式サイトですの。",
  "scene_02_02.wav": "あの宇宙バスケの映画だ！",
  "scene_02_03.wav": "あのサイト、合計わずか約2キロバイトですの。エイチティーエムエルとテーブルレイアウトだけで作られていましたわ。",
  "scene_02_04.wav": "2キロバイト！？ 写真1枚より軽いじゃん！",
  "scene_02_05.wav": "面白いことに今でもそのサイトは閲覧可能ですわ。クリックした瞬間に表示されますの。",
  "scene_02_06.wav": "30年前のサイトが今でも見られるんだ。すごいね。",
  "scene_02_07.wav": "シンプルなエイチティーエムエルだからこそ、どんな環境でも壊れずに動きますの。",
  "scene_02_08.wav": "じゃあ2キロバイトから2,600キロバイトって1,300倍になってるの？",
  "scene_02_09.wav": "もちろん当時と今ではウェブにできることが全く違いますから、単純比較はできませんわ。",
  "scene_02_10.wav": "でも「ページを表示するだけ」のコストがここまで増えたのは事実ですの。",
  "scene_03_00.wav": "何がそんなに重いの？ 画像が大きいとか？",
  "scene_03_01.wav": "画像も大きいですけれど、特に注目すべきはジャバスクリプトの量ですわ。",
  "scene_03_02.wav": "エイチティーティーピー アーカイブによると、2024年のジェイエス転送量の中央値はデスクトップで約560キロバイトですの。",
  "scene_03_03.wav": "ジャバスクリプトだけで560キロバイトも？",
  "scene_03_04.wav": "しかもこれはジージップ圧縮後の値ですわ。ブラウザが展開すると数倍になりますの。",
  "scene_03_05.wav": "ブラウザはこの大量のジェイエスをダウンロードして、解析して、コンパイルして、実行しますの。",
  "scene_03_06.wav": "4段階も処理があるんだ。そりゃファンも回るわけだね。",
  "scene_03_07.wav": "特にスマートフォンでは、この負荷がもっと深刻ですわ。",
  "scene_03_08.wav": "ピーシーの何分の1かの処理能力で同じジェイエスを実行しなければなりませんの。",
  "scene_03_09.wav": "スマホでウェブサイト開くと、なかなか操作できない時あるよね。あれが原因なのか。",
  "scene_03_10.wav": "ちなみにトンスキーさんの2024年の調査によると、スラックのウェブ版はジェイエスだけで55メガバイトですの。",
  "scene_03_11.wav": "55メガバイト！？ ただのチャットアプリなのに？",
  "scene_03_12.wav": "1996年のスリーディーゲーム、クエイクワン本分と同じサイズですわ。",
  "scene_03_13.wav": "ゲーム1本と同じ量のジェイエスをチャットのために読み込んでるのか。",
  "scene_04_00.wav": "そしてこの重さは、ユーザーの行動にも直結しますの。",
  "scene_04_01.wav": "グーグルの調査によると、ページ読み込みが1秒から3秒に遅れると直帰率が32パーセント増加しますわ。",
  "scene_04_02.wav": "たった2秒で3割も離脱するの？",
  "scene_04_03.wav": "5秒になると90パーセント増加ですの。ユーザーは本当に待ってくれませんわ。",
  "scene_04_04.wav": "確かにぼくも3秒待って表示されないサイトは閉じちゃうのだ。",
  "scene_04_05.wav": "だからグーグルはコア ウェブ バイタルズという指標を設けて、表示速度をランキング要因にしていますわ。",
  "scene_04_06.wav": "サイトの重さは検索順位にも影響するんですの。",
  "scene_04_07.wav": "重いサイトはグーグル検索でも不利になるんだ。それは深刻だね。",
  "scene_04_08.wav": "アマゾンの調査では、表示が0.1秒遅れるだけで売上が1パーセント減るというデータもありますわ。",
  "scene_04_09.wav": "0.1秒で1パーセント！ アマゾンの規模だととんでもない額だよね。",
  "scene_05_00.wav": "ではなぜウェブページがここまで重くなったのか、歴史を振り返ってみましょう。",
  "scene_05_01.wav": "昔は軽かったんだよね。何がきっかけで変わったの？",
  "scene_05_02.wav": "大きな転換点は2005年頃ですわ。エイジャックスという技術が広まりましたの。",
  "scene_05_03.wav": "ページ全体をリロードしなくても、一部だけ更新できる技術ですわ。",
  "scene_05_04.wav": "あ、ジーメールとかグーグル マップスがそれだよね。",
  "scene_05_05.wav": "ええ。エイジャックスのおかげで、ウェブは「文書を読む場所」から「アプリを動かす場所」に変わりましたの。",
  "scene_05_06.wav": "でもアプリらしく動かすには、それだけ大量のジャバスクリプトが必要になりますわ。",
  "scene_05_07.wav": "便利になった代わりに、コードがどんどん増えていったんだね。",
  "scene_05_08.wav": "そして2013年にフェイスブックがリアクトを公開しますの。ここからフレームワーク時代が本格化しますわ。",
  "scene_05_09.wav": "リアクト、ビュー、アンギュラー。この辺が一気に出てきた時代だね。",
  "scene_06_00.wav": "そして2010年代、エスピーエーが主流になりますの。シングル ページ アプリケーションの略ですわ。",
  "scene_06_01.wav": "エスピーエーってよく聞くけど、普通のサイトと何が違うの？",
  "scene_06_02.wav": "従来のサイトは、リンクをクリックするたびにサーバーから新しいエイチティーエムエルが届いていましたの。",
  "scene_06_03.wav": "エスピーエーは最初にアプリ全体のジャバスクリプトをまとめて読み込みますわ。",
  "scene_06_04.wav": "以降の画面遷移はジャバスクリプトがブラウザの中だけで処理しますの。",
  "scene_06_05.wav": "だからページ移動がサクサク感じるんだね。",
  "scene_06_06.wav": "その代わり、初回の読み込みでアプリ丸ごとのジェイエスをダウンロードしなければなりませんの。",
  "scene_06_07.wav": "サクサク感の代償として最初が重くなるわけか。なるほど。",
  "scene_06_08.wav": "ノーションやスラックのウェブ版が初回表示に時間がかかるのは、まさにこの仕組みですの。",
  "scene_07_00.wav": "重くなった原因を大きく3つに整理しますわ。",
  "scene_07_01.wav": "1つ目、フレームワークの多層化ですの。",
  "scene_07_02.wav": "リアクト本体に加えて、ルーター、状態管理ライブラリ、ユーアイコンポーネント集と積み重なりますわ。",
  "scene_07_03.wav": "2つ目、依存パッケージの爆発ですの。",
  "scene_07_04.wav": "小さな機能1つのためにライブラリを追加する文化が広まりましたわ。",
  "scene_07_05.wav": "3つ目、サードパーティスクリプトですの。",
  "scene_07_06.wav": "広告、アナリティクス、エービーテスト、チャットウィジェットなどが次々と読み込まれますわ。",
  "scene_07_07.wav": "3つ全部が重なって膨れ上がっていくんだね。",
  "scene_07_08.wav": "しかもどれか1つだけを減らしても、全体のサイズはなかなか小さくならないのが厄介ですわ。",
  "scene_08_00.wav": "フレームワークってそんなに大きいの？",
  "scene_08_01.wav": "フレームワーク本体の圧縮後サイズを比べてみましょう。",
  "scene_08_02.wav": "リアクト 18とリアクトドムのセットで約44キロバイト、ビュー 3が約33キロバイト、アンギュラーは約60キロバイトですわ。",
  "scene_08_03.wav": "数十キロバイトなら大したことなさそうだけど。",
  "scene_08_04.wav": "フレームワーク単体ならそうですわ。でも実際のアプリではこれが出発点にすぎませんの。",
  "scene_08_05.wav": "ルーターを足して15キロバイト、状態管理で10キロバイト、ユーアイライブラリで100キロバイト以上。あっという間に数百キロバイトですわ。",
  "scene_08_06.wav": "トッピングがどんどん増えていく感じだね。",
  "scene_08_07.wav": "しかも依存ライブラリにはコードの重複もありますから、実際にはもっと膨らみますの。",
  "scene_09_00.wav": "もう1つ象徴的なのが、ノード モジュールズフォルダの問題ですわ。",
  "scene_09_01.wav": "あの異常に巨大なフォルダだ。「宇宙で最も重い物体」ってネタがあるよね。",
  "scene_09_02.wav": "クリエイト リアクト アップでプロジェクトを作ると、初期状態で約1,400パッケージが入りますの。",
  "scene_09_03.wav": "容量にして200メガバイト超。コード1行も書いていない状態でですわ。",
  "scene_09_04.wav": "ハロー ワールドを表示するだけなのに1,400パッケージ！？",
  "scene_09_05.wav": "直接使うのは数十パッケージでも、それぞれがさらに別のパッケージに依存していますの。",
  "scene_09_06.wav": "依存の依存の依存、いわゆる「依存地獄」ですわね。",
  "scene_09_07.wav": "ねずみ算式に増えていくんだ。怖いね。",
  "scene_09_08.wav": "エヌピーエムのレジストリには2024年時点で200万以上のパッケージが登録されていますわ。",
  "scene_09_09.wav": "200万！？ そんなにあるんだ。",
  "scene_10_00.wav": "この依存の脆さを象徴する事件がありますわ。2016年のレフトパッド事件ですの。",
  "scene_10_01.wav": "レフトパッド？ 何があったの？",
  "scene_10_02.wav": "文字列の左側をスペースで埋めるだけの、たった11行のエヌピーエムパッケージがありましたの。",
  "scene_10_03.wav": "作者がエヌピーエムから削除したところ、リアクトやバベルなど世界中のプロジェクトがビルドできなくなりましたわ。",
  "scene_10_04.wav": "11行のコードが消えただけで世界が止まったの！？",
  "scene_10_05.wav": "何千ものパッケージが間接的にレフトパッドに依存していたんですの。",
  "scene_10_06.wav": "この事件は、現代のウェブ開発がいかに薄い依存関係の上に成り立っているかを示しましたわ。",
  "scene_10_07.wav": "自分が使ってるライブラリの中身を全部把握するのは無理だよね。",
  "scene_10_08.wav": "この事件の後、エヌピーエムは一度公開したパッケージを簡単に削除できないようルールを変更しましたわ。",
  "scene_10_09.wav": "さすがに対策が取られたんだね。でも根本的な依存の問題は残ってそうだよね。",
  "scene_11_00.wav": "ただし、この重さに対する反動も確実に起きていますわ。",
  "scene_11_01.wav": "みんなやっぱり重いって思ってたんだね。",
  "scene_11_02.wav": "「本当にこのサイトにエスピーエーが必要なのか？」という問い直しが広がっていますの。",
  "scene_11_03.wav": "そこから新しい軽量なアプローチがいくつも生まれていますわ。",
  "scene_11_04.wav": "昔に戻ろうって話ではないんだよね？",
  "scene_11_05.wav": "単純に戻るのではなく、エスピーエーの良さを残しつつ軽くする工夫ですの。",
  "scene_12_00.wav": "代表的な3つを紹介しますわ。まずエイチティーエムエックスですの。",
  "scene_12_01.wav": "サーバーからエイチティーエムエルの断片を受け取って部分更新する方式ですわ。本体わずか14キロバイトですの。",
  "scene_12_02.wav": "14キロバイトでエスピーエーみたいなことができるの？ すごいね。",
  "scene_12_03.wav": "エイチティーエムエルをそのままやり取りするので、ジェイソンのパースも仮想ドムの差分計算も不要ですの。",
  "scene_12_04.wav": "次にスベルトですわ。コンパイル時にフレームワーク自身のコードを取り除きますの。",
  "scene_12_05.wav": "出力されるのは必要最小限のジャバスクリプトだけ。ランタイムがほぼゼロですわ。",
  "scene_12_06.wav": "フレームワークなのに最終的にフレームワークが消えるって面白いね。",
  "scene_12_07.wav": "3つ目はアストロですの。デフォルトでジャバスクリプトを一切ブラウザに送りませんわ。",
  "scene_12_08.wav": "ボタンやフォームなど、本当に動きが必要な部分だけを後から有効化しますの。",
  "scene_12_09.wav": "デフォルトでジェイエス0キロバイトってすごい発想だね。必要なところだけって賢いなあ。",
  "scene_13_00.wav": "じゃあリアクトはもう使わない方がいいの？",
  "scene_13_01.wav": "そうではありませんわ。リアクトは大規模なウェブアプリを効率的に開発する素晴らしいツールですの。",
  "scene_13_02.wav": "ノーションやフィグマのような複雑なアプリにはエスピーエーの恩恵が大きいですわ。",
  "scene_13_03.wav": "問題は「すべてのサイトにエスピーエーフレームワークが必要か？」という判断の部分ですの。",
  "scene_13_04.wav": "ブログとか企業サイトにはオーバーキルかもってこと？",
  "scene_13_05.wav": "その通りですわ。道具は適材適所で選ぶのが大切ですの。",
  "scene_13_06.wav": "ちなみにリアクト自身もサーバー コンポーネンツという仕組みで軽量化を進めていますわ。",
  "scene_13_07.wav": "サーバー側でレンダリングして、クライアントに送るジェイエスを減らす方向ですの。",
  "scene_13_08.wav": "リアクト側も重さの問題を意識してるんだね。",
  "scene_13_09.wav": "実際にサーバー コンポーネンツを導入した企業で、ジェイエスバンドルが62パーセント減少した事例もありますわ。",
  "scene_13_10.wav": "どのツールにも得意な場面と苦手な場面がありますの。万能な正解はありませんわ。",
  "scene_14_00.wav": "今日の内容を3つにまとめますわ。",
  "scene_14_01.wav": "1つ目、ウェブページはこの15年で5倍以上に肥大化しましたの。特にジャバスクリプトの増加が大きいですわ。",
  "scene_14_02.wav": "2つ目、エスピーエーの普及、依存パッケージの連鎖、サードパーティスクリプトが主な原因ですの。",
  "scene_14_03.wav": "3つ目、エイチティーエムエックスやスベルト、アストロなど軽量化を目指す新しい技術が生まれていますわ。",
  "scene_14_04.wav": "重くなった理由がわかると、対策も見えてくるね。",
  "scene_14_05.wav": "大切なのは、作るものの規模や用途に合った技術を選ぶことですわ。",
  "scene_14_06.wav": "全部エスピーエーにする必要はないってことだね。",
  "scene_14_07.wav": "ええ。静的なエイチティーエムエルで十分な部分と、リッチなユーアイが必要な部分を見極めることですの。",
  "scene_15_00.wav": "スペース ジャムが2キロバイトだったのが一番衝撃だったのだ。",
  "scene_15_01.wav": "あのサイトは今見ると逆に新鮮ですわ。クリックした瞬間に表示される快適さがありますの。",
  "scene_15_02.wav": "ぼくも次に何か作るときは「本当にこのライブラリ必要？」って考えてみるのだ。",
  "scene_15_03.wav": "その一歩がとても大事ですわ。最初はエイチティーエムエルとシーエスエスだけで十分なことも意外と多いですの。",
  "scene_15_04.wav": "ウェブ、もうちょっと軽くなってほしいのだ。",
  "scene_15_05.wav": "きっとなりますわ。技術は振り子のように揺れながら、ちょうどいい場所を探していくものですの。",
  "scene_15_06.wav": "今はちょうど「軽く」の方に戻り始めたところなんだね。",
  "scene_15_07.wav": "今日もご視聴ありがとうございました。チャンネル登録と高評価をお願いしますわ。",
  "scene_15_08.wav": "またねなのだ。"
}